geocli/__init__.py
geocli/__main__.py
geocli/geocli_driver.py
geocli-1.0.1.dist-info/LICENSE
geocli-1.0.1.dist-info/METADATA
geocli-1.0.1.dist-info/WHEEL
geocli-1.0.1.dist-info/dependency_links.txt
geocli-1.0.1.dist-info/entry_points.txt
geocli-1.0.1.dist-info/top_level.txt
geocli-1.0.1.dist-info/RECORD
