Metadata-Version: 2.1
Name: geocli
Version: 1.0.1
Summary: A simple commandline app for geocoding
Home-page: https://github.com/expandaventures/geocoding-cli
Author: Paco Valdez
Author-email: pacofvf@gmail.com
License: GPLv3
Download-URL: https://github.com/expandaventures/geocoding-cli/archive/1.0.0.tar.gz
Platform: UNKNOWN
Classifier: License :: OSI Approved :: GNU General Public License v3 or later (GPLv3+)
Classifier: Programming Language :: Python :: 2.7
Classifier: Programming Language :: Python :: 3
Classifier: Programming Language :: Python :: 3.7
Requires-Python: >=2.7
Requires-Dist: certifi (==2020.12.5)
Requires-Dist: chardet (==4.0.0)
Requires-Dist: click (==7.1.2)
Requires-Dist: idna (==2.10)
Requires-Dist: requests (==2.25.1)
Requires-Dist: urllib3 (==1.26.3)
